fapi_cli/__init__.py
fapi_cli/__main__.py
fapi_cli/_version.py
fapi_cli/cli.py
fapi_cli/version.py
fapi_cli-0.2.1.dist-info/METADATA
fapi_cli-0.2.1.dist-info/WHEEL
fapi_cli-0.2.1.dist-info/entry_points.txt
fapi_cli-0.2.1.dist-info/licenses/LICENSE
fapi_cli-0.2.1.dist-info/RECORD
