Metadata-Version: 2.4
Name: fapi-cli
Version: 0.2.1
Summary: Invoke FastAPI endpoints without starting a server.
Project-URL: Homepage, https://github.com/WATA-saito/fapi-cli
Project-URL: Repository, https://github.com/WATA-saito/fapi-cli
Project-URL: Documentation, https://github.com/WATA-saito/fapi-cli#readme
Project-URL: Issues, https://github.com/WATA-saito/fapi-cli/issues
Project-URL: Bug Tracker, https://github.com/WATA-saito/fapi-cli/issues
Author: Wataru
License: MIT
License-File: LICENSE
Keywords: api-testing,cli,fastapi,http-client,testclient,testing
Classifier: Development Status :: 3 - Alpha
Classifier: Intended Audience :: Developers
Classifier: License :: OSI Approved :: MIT License
Classifier: Programming Language :: Python
Classifier: Programming Language :: Python :: 3
Classifier: Programming Language :: Python :: 3.9
Classifier: Programming Language :: Python :: 3.10
Classifier: Programming Language :: Python :: 3.11
Classifier: Programming Language :: Python :: 3.12
Classifier: Programming Language :: Python :: 3.13
Classifier: Programming Language :: Python :: 3.14
Classifier: Topic :: Software Development :: Testing
Classifier: Topic :: Utilities
Requires-Python: >=3.9
Requires-Dist: fastapi<1.0,>=0.100.0
Requires-Dist: httpx>=0.23
Requires-Dist: typer>=0.9.0
Provides-Extra: dev
Requires-Dist: build>=1.2; extra == 'dev'
Requires-Dist: packaging>=21.0; extra == 'dev'
Requires-Dist: pytest-cov>=4.1; extra == 'dev'
Requires-Dist: pytest>=7.4; extra == 'dev'
Requires-Dist: python-multipart<1.0,>=0.0.6; extra == 'dev'
Requires-Dist: tox>=4.0; extra == 'dev'
Requires-Dist: twine>=5.0; extra == 'dev'
Provides-Extra: form
Requires-Dist: python-multipart<1.0,>=0.0.6; extra == 'form'
